jdDesktopEntryEdit/AboutDialog.py
jdDesktopEntryEdit/EditActionDialog.py
jdDesktopEntryEdit/EditKeywordsTranslationDialog.py
jdDesktopEntryEdit/Environment.py
jdDesktopEntryEdit/Functions.py
jdDesktopEntryEdit/Icon.svg
jdDesktopEntryEdit/Languages.py
jdDesktopEntryEdit/ListEditWidget.py
jdDesktopEntryEdit/MainWindow.py
jdDesktopEntryEdit/ManageTemplatesWindow.py
jdDesktopEntryEdit/PreviewDialog.py
jdDesktopEntryEdit/Settings.py
jdDesktopEntryEdit/SettingsDialog.py
jdDesktopEntryEdit/TranslateDialog.py
jdDesktopEntryEdit/ValidationDialog.py
jdDesktopEntryEdit/WelcomeDialog.py
jdDesktopEntryEdit/__init__.py
jdDesktopEntryEdit/__main__.py
jdDesktopEntryEdit/version.txt
jdDesktopEntryEdit/data/categories.txt
jdDesktopEntryEdit/data/changelog.html
jdDesktopEntryEdit/data/translators.json
jdDesktopEntryEdit/dbus/FreedesktopApplicationInterface.py
jdDesktopEntryEdit/dbus/FreedesktopApplicationInterface.xml
jdDesktopEntryEdit/dbus/jdDesktopEntryEditInterface.py
jdDesktopEntryEdit/dbus/jdDesktopEntryEditInterface.xml
jdDesktopEntryEdit/translations/jdDesktopEntryEdit_de.qm
jdDesktopEntryEdit/translations/jdDesktopEntryEdit_nl.qm
jdDesktopEntryEdit/ui_compiled/AboutDialog.py
jdDesktopEntryEdit/ui_compiled/EditActionDialog.py
jdDesktopEntryEdit/ui_compiled/MainWindow.py
jdDesktopEntryEdit/ui_compiled/ManageTemplatesWindow.py
jdDesktopEntryEdit/ui_compiled/PreviewDialog.py
jdDesktopEntryEdit/ui_compiled/SettingsDialog.py
jdDesktopEntryEdit/ui_compiled/TranslateDialog.py
jdDesktopEntryEdit/ui_compiled/ValidationDialog.py
jdDesktopEntryEdit/ui_compiled/WelcomeDialog.py
jdDesktopEntryEdit/ui_compiled/__init__.py
jddesktopentryedit-1.7.dist-info/licenses/LICENSE
jddesktopentryedit-1.7.dist-info/METADATA
jddesktopentryedit-1.7.dist-info/WHEEL
jddesktopentryedit-1.7.dist-info/entry_points.txt
jddesktopentryedit-1.7.dist-info/top_level.txt
jddesktopentryedit-1.7.dist-info/RECORD
