Metadata-Version: 2.4
Name: jdDesktopEntryEdit
Version: 1.7
Summary: A graphical Program to create and edit Desktop Entries
Author-email: JakobDev <jakobdev@gmx.de>
License: GPL-3
Project-URL: Homepage, https://jakobdev.codeberg.page/work/app/jdDesktopEntryEdit
Project-URL: Source, https://codeberg.org/JakobDev/jdDesktopEntryEdit
Project-URL: Issues, https://codeberg.org/JakobDev/jdDesktopEntryEdit/issues
Project-URL: Translate, https://translate.codeberg.org/projects/jdDesktopEntryEdit
Project-URL: Donation, https://ko-fi.com/jakobdev
Keywords: JakobDev,Linux,.desktop,freedesktop
Classifier: Development Status :: 5 - Production/Stable
Classifier: Intended Audience :: Developers
Classifier: Environment :: Other Environment
Classifier: License :: OSI Approved :: GNU General Public License v3 (GPLv3)
Classifier: Operating System :: POSIX
Classifier: Operating System :: POSIX :: BSD
Classifier: Operating System :: POSIX :: Linux
Classifier: Programming Language :: Python :: 3
Classifier: Programming Language :: Python :: 3.10
Classifier: Programming Language :: Python :: 3.11
Classifier: Programming Language :: Python :: 3.12
Classifier: Programming Language :: Python :: 3.13
Classifier: Programming Language :: Python :: 3 :: Only
Classifier: Programming Language :: Python :: Implementation :: CPython
Requires-Python: >=3.10
License-File: LICENSE
Requires-Dist: PyQt6
Requires-Dist: desktop-entry-lib
Dynamic: license-file
